{"type": "GameHistory", "white_name": "apltest68", "black_name": "apltest17", "senses": {"true": [0, 37, 39, 45, 0, 26, 52, 60, 17, 61, 56, 26, 50, 3, 1, 17, 13, 16, 22, 45, 15, 1, 15, 20, 48, 47, 44, 61, 19, 40, 53, 48, 47, 19, 35, 25, 13, 21, 41, 19, 40, 19, 12, 20, 41, 47, 22, 47, 2, 13, 1, 7], "false": [4, 12, 43, 50, 8, 2, 4, 1, 55, 49, 42, 58, 42, 34, 41, 19, 16, 47, 2, 48, 47, 8, 54, 46, 42, 26, 13, 26, 30, 47, 6, 35, 28, 8, 30, 47, 32, 42, 56, 0, 49, 24, 32, 51, 37, 42, 63, 17, 58, 47, 34, 38]}, "sense_results": {"true": [[[8, {"type": "Piece", "value": "P"}], [9, {"type": "Piece", "value": "P"}], [0, {"type": "Piece", "value": "R"}], [1, {"type": "Piece", "value": "N"}]], [[44, null], [45, null], [46, null], [36, null], [37, null], [38, null], [28, null], [29, null], [30, null]], [[46, null], [47, null], [38, {"type": "Piece", "value": "p"}], [39, null], [30, null], [31, null]], [[52, {"type": "Piece", "value": "p"}], [53, {"type": "Piece", "value": "p"}], [54, null], [44, null], [45, null], [46, null], [36, null], [37, null], [38, {"type": "Piece", "value": "p"}]], [[8, {"type": "Piece", "value": "P"}], [9, null], [0, {"type": "Piece", "value": "R"}], [1, null]], [[33, null], [34, {"type": "Piece", "value": "n"}], [35, null], [25, {"type": "Piece", "value": "P"}], [26, null], [27, null], [17, null], [18, null], [19, null]], [[59, {"type": "Piece", "value": "q"}], [60, {"type": "Piece", "value": "k"}], [61, {"type": "Piece", "value": "b"}], [51, {"type": "Piece", "value": "p"}], [52, {"type": "Piece", "value": "p"}], [53, {"type": "Piece", "value": "p"}], [43, null], [44, null], [45, {"type": "Piece", "value": "n"}]], [[59, {"type": "Piece", "value": "q"}], [60, {"type": "Piece", "value": "k"}], [61, {"type": "Piece", "value": "b"}], [51, {"type": "Piece", "value": "p"}], [52, {"type": "Piece", "value": "p"}], [53, {"type": "Piece", "value": "p"}]], [[24, null], [25, {"type": "Piece", "value": "P"}], [26, null], [16, {"type": "Piece", "value": "N"}], [17, null], [18, null], [8, {"type": "Piece", "value": "P"}], [9, null], [10, {"type": "Piece", "value": "P"}]], [[60, {"type": "Piece", "value": "k"}], [61, {"type": "Piece", "value": "b"}], [62, {"type": "Piece", "value": "r"}], [52, {"type": "Piece", "value": "p"}], [53, {"type": "Piece", "value": "p"}], [54, null]], [[56, {"type": "Piece", "value": "r"}], [57, null], [48, null], [49, {"type": "Piece", "value": "p"}]], [[33, null], [34, {"type": "Piece", "value": "n"}], [35, null], [25, {"type": "Piece", "value": "P"}], [26, null], [27, null], [17, null], [18, null], [19, {"type": "Piece", "value": "P"}]], [[57, null], [58, {"type": "Piece", "value": "b"}], [59, {"type": "Piece", "value": "q"}], [49, {"type": "Piece", "value": "p"}], [50, {"type": "Piece", "value": "p"}], [51, {"type": "Piece", "value": "p"}], [41, {"type": "Piece", "value": "N"}], [42, null], [43, null]], [[10, {"type": "Piece", "value": "P"}], [11, null], [12, {"type": "Piece", "value": "P"}], [2, null], [3, {"type": "Piece", "value": "Q"}], [4, null]], [[8, {"type": "Piece", "value": "P"}], [9, null], [10, {"type": "Piece", "value": "P"}], [0, null], [1, {"type": "Piece", "value": "R"}], [2, null]], [[24, null], [25, {"type": "Piece", "value": "P"}], [26, null], [16, {"type": "Piece", "value": "B"}], [17, {"type": "Piece", "value": "P"}], [18, null], [8, {"type": "Piece", "value": "P"}], [9, null], [10, null]], [[20, null], [21, null], [22, {"type": "Piece", "value": "P"}], [12, {"type": "Piece", "value": "P"}], [13, {"type": "Piece", "value": "K"}], [14, null], [4, null], [5, {"type": "Piece", "value": "B"}], [6, {"type": "Piece", "value": "N"}]], [[24, null], [25, {"type": "Piece", "value": "P"}], [16, {"type": "Piece", "value": "B"}], [17, {"type": "Piece", "value": "P"}], [8, {"type": "Piece", "value": "P"}], [9, null]], [[29, {"type": "Piece", "value": "P"}], [30, null], [31, null], [21, null], [22, {"type": "Piece", "value": "P"}], [23, {"type": "Piece", "value": "P"}], [13, {"type": "Piece", "value": "K"}], [14, null], [15, null]], [[52, {"type": "Piece", "value": "p"}], [53, {"type": "Piece", "value": "p"}], [54, null], [44, null], [45, {"type": "Piece", "value": "n"}], [46, null], [36, null], [37, null], [38, {"type": "Piece", "value": "p"}]], [[22, {"type": "Piece", "value": "P"}], [23, {"type": "Piece", "value": "P"}], [14, null], [15, null], [6, {"type": "Piece", "value": "N"}], [7, {"type": "Piece", "value": "R"}]], [[8, {"type": "Piece", "value": "P"}], [9, null], [10, null], [0, null], [1, {"type": "Piece", "value": "R"}], [2, null]], [[22, {"type": "Piece", "value": "P"}], [23, {"type": "Piece", "value": "P"}], [14, {"type": "Piece", "value": "K"}], [15, null], [6, {"type": "Piece", "value": "N"}], [7, {"type": "Piece", "value": "R"}]], [[27, null], [28, null], [29, {"type": "Piece", "value": "P"}], [19, {"type": "Piece", "value": "P"}], [20, null], [21, null], [11, null], [12, {"type": "Piece", "value": "P"}], [13, null]], [[56, null], [57, null], [48, null], [49, {"type": "Piece", "value": "p"}], [40, {"type": "Piece", "value": "r"}], [41, {"type": "Piece", "value": "p"}]], [[54, {"type": "Piece", "value": "r"}], [55, {"type": "Piece", "value": "p"}], [46, null], [47, null], [38, {"type": "Piece", "value": "p"}], [39, null]], [[51, {"type": "Piece", "value": "p"}], [52, {"type": "Piece", "value": "p"}], [53, {"type": "Piece", "value": "p"}], [43, null], [44, null], [45, null], [35, null], [36, null], [37, null]], [[60, {"type": "Piece", "value": "k"}], [61, {"type": "Piece", "value": "b"}], [62, null], [52, {"type": "Piece", "value": "p"}], [53, {"type": "Piece", "value": "p"}], [54, {"type": "Piece", "value": "r"}]], [[26, null], [27, null], [28, null], [18, null], [19, {"type": "Piece", "value": "P"}], [20, null], [10, null], [11, null], [12, {"type": "Piece", "value": "P"}]], [[48, null], [49, {"type": "Piece", "value": "p"}], [40, null], [41, {"type": "Piece", "value": "p"}], [32, null], [33, {"type": "Piece", "value": "P"}]], [[60, {"type": "Piece", "value": "k"}], [61, {"type": "Piece", "value": "b"}], [62, null], [52, {"type": "Piece", "value": "p"}], [53, {"type": "Piece", "value": "p"}], [54, null], [44, null], [45, null], [46, null]], [[56, {"type": "Piece", "value": "r"}], [57, null], [48, null], [49, {"type": "Piece", "value": "p"}], [40, null], [41, {"type": "Piece", "value": "p"}]], [[54, null], [55, null], [46, null], [47, {"type": "Piece", "value": "p"}], [38, {"type": "Piece", "value": "r"}], [39, null]], [[26, null], [27, null], [28, {"type": "Piece", "value": "P"}], [18, null], [19, {"type": "Piece", "value": "P"}], [20, null], [10, null], [11, null], [12, {"type": "Piece", "value": "Q"}]], [[42, null], [43, null], [44, null], [34, null], [35, null], [36, null], [26, null], [27, null], [28, {"type": "Piece", "value": "P"}]], [[32, null], [33, {"type": "Piece", "value": "P"}], [34, null], [24, null], [25, null], [26, null], [16, {"type": "Piece", "value": "B"}], [17, {"type": "Piece", "value": "p"}], [18, null]], [[20, null], [21, null], [22, null], [12, null], [13, {"type": "Piece", "value": "R"}], [14, {"type": "Piece", "value": "K"}], [4, null], [5, {"type": "Piece", "value": "B"}], [6, {"type": "Piece", "value": "R"}]], [[28, {"type": "Piece", "value": "P"}], [29, {"type": "Piece", "value": "P"}], [30, {"type": "Piece", "value": "P"}], [20, null], [21, null], [22, null], [12, null], [13, {"type": "Piece", "value": "R"}], [14, {"type": "Piece", "value": "K"}]], [[48, null], [49, {"type": "Piece", "value": "p"}], [50, null], [40, {"type": "Piece", "value": "r"}], [41, {"type": "Piece", "value": "p"}], [42, null], [32, null], [33, {"type": "Piece", "value": "P"}], [34, null]], [[26, null], [27, null], [28, {"type": "Piece", "value": "P"}], [18, null], [19, {"type": "Piece", "value": "P"}], [20, null], [10, null], [11, null], [12, null]], [[48, null], [49, {"type": "Piece", "value": "p"}], [40, {"type": "Piece", "value": "r"}], [41, {"type": "Piece", "value": "p"}], [32, null], [33, {"type": "Piece", "value": "r"}]], [[26, null], [27, {"type": "Piece", "value": "P"}], [28, {"type": "Piece", "value": "P"}], [18, null], [19, null], [20, null], [10, null], [11, null], [12, null]], [[19, null], [20, null], [21, null], [11, null], [12, null], [13, {"type": "Piece", "value": "R"}], [3, null], [4, null], [5, {"type": "Piece", "value": "B"}]], [[27, {"type": "Piece", "value": "P"}], [28, {"type": "Piece", "value": "P"}], [29, {"type": "Piece", "value": "P"}], [19, null], [20, null], [21, null], [11, null], [12, null], [13, {"type": "Piece", "value": "R"}]], [[48, null], [49, {"type": "Piece", "value": "p"}], [50, {"type": "Piece", "value": "q"}], [40, {"type": "Piece", "value": "r"}], [41, {"type": "Piece", "value": "Q"}], [42, null], [32, null], [33, null], [34, null]], [[54, null], [55, null], [46, null], [47, {"type": "Piece", "value": "p"}], [38, null], [39, null]], [[29, {"type": "Piece", "value": "P"}], [30, {"type": "Piece", "value": "n"}], [31, null], [21, null], [22, null], [23, {"type": "Piece", "value": "P"}], [13, {"type": "Piece", "value": "R"}], [14, null], [15, {"type": "Piece", "value": "K"}]], [[54, null], [55, null], [46, null], [47, {"type": "Piece", "value": "p"}], [38, null], [39, null]], [[9, null], [10, null], [11, null], [1, null], [2, null], [3, null]], [[20, null], [21, null], [22, null], [12, null], [13, {"type": "Piece", "value": "R"}], [14, null], [4, null], [5, null], [6, null]], [[8, {"type": "Piece", "value": "p"}], [9, null], [10, null], [0, null], [1, {"type": "Piece", "value": "R"}], [2, null]], [[14, null], [15, {"type": "Piece", "value": "K"}], [6, null], [7, null]]], "false": [[[11, {"type": "Piece", "value": "P"}], [12, {"type": "Piece", "value": "P"}], [13, {"type": "Piece", "value": "P"}], [3, {"type": "Piece", "value": "Q"}], [4, {"type": "Piece", "value": "K"}], [5, {"type": "Piece", "value": "B"}]], [[19, null], [20, null], [21, null], [11, {"type": "Piece", "value": "P"}], [12, {"type": "Piece", "value": "P"}], [13, {"type": "Piece", "value": "P"}], [3, {"type": "Piece", "value": "Q"}], [4, {"type": "Piece", "value": "K"}], [5, {"type": "Piece", "value": "B"}]], [[50, {"type": "Piece", "value": "p"}], [51, {"type": "Piece", "value": "p"}], [52, {"type": "Piece", "value": "p"}], [42, null], [43, null], [44, null], [34, null], [35, null], [36, null]], [[57, null], [58, {"type": "Piece", "value": "b"}], [59, {"type": "Piece", "value": "q"}], [49, {"type": "Piece", "value": "p"}], [50, {"type": "Piece", "value": "p"}], [51, {"type": "Piece", "value": "p"}], [41, null], [42, null], [43, null]], [[16, {"type": "Piece", "value": "N"}], [17, null], [8, {"type": "Piece", "value": "P"}], [9, null], [0, {"type": "Piece", "value": "R"}], [1, null]], [[9, null], [10, {"type": "Piece", "value": "P"}], [11, {"type": "Piece", "value": "P"}], [1, null], [2, {"type": "Piece", "value": "B"}], [3, {"type": "Piece", "value": "Q"}]], [[11, {"type": "Piece", "value": "P"}], [12, {"type": "Piece", "value": "P"}], [13, null], [3, {"type": "Piece", "value": "Q"}], [4, {"type": "Piece", "value": "K"}], [5, {"type": "Piece", "value": "B"}]], [[8, {"type": "Piece", "value": "P"}], [9, null], [10, {"type": "Piece", "value": "P"}], [0, {"type": "Piece", "value": "R"}], [1, null], [2, {"type": "Piece", "value": "B"}]], [[62, {"type": "Piece", "value": "r"}], [63, null], [54, null], [55, {"type": "Piece", "value": "p"}], [46, null], [47, null]], [[56, {"type": "Piece", "value": "r"}], [57, null], [58, {"type": "Piece", "value": "b"}], [48, {"type": "Piece", "value": "p"}], [49, {"type": "Piece", "value": "p"}], [50, {"type": "Piece", "value": "p"}], [40, null], [41, {"type": "Piece", "value": "N"}], [42, null]], [[49, {"type": "Piece", "value": "p"}], [50, {"type": "Piece", "value": "p"}], [51, {"type": "Piece", "value": "p"}], [41, {"type": "Piece", "value": "N"}], [42, null], [43, null], [33, null], [34, {"type": "Piece", "value": "n"}], [35, null]], [[57, null], [58, {"type": "Piece", "value": "b"}], [59, {"type": "Piece", "value": "q"}], [49, {"type": "Piece", "value": "p"}], [50, {"type": "Piece", "value": "p"}], [51, {"type": "Piece", "value": "p"}]], [[49, {"type": "Piece", "value": "p"}], [50, {"type": "Piece", "value": "p"}], [51, {"type": "Piece", "value": "p"}], [41, {"type": "Piece", "value": "N"}], [42, null], [43, null], [33, null], [34, {"type": "Piece", "value": "n"}], [35, null]], [[41, {"type": "Piece", "value": "N"}], [42, null], [43, null], [33, null], [34, null], [35, null], [25, {"type": "Piece", "value": "P"}], [26, null], [27, null]], [[48, null], [49, {"type": "Piece", "value": "p"}], [50, {"type": "Piece", "value": "p"}], [40, {"type": "Piece", "value": "p"}], [41, {"type": "Piece", "value": "N"}], [42, null], [32, null], [33, null], [34, null]], [[26, null], [27, null], [28, null], [18, null], [19, {"type": "Piece", "value": "P"}], [20, null], [10, null], [11, null], [12, {"type": "Piece", "value": "P"}]], [[24, null], [25, {"type": "Piece", "value": "P"}], [16, {"type": "Piece", "value": "B"}], [17, {"type": "Piece", "value": "P"}], [8, {"type": "Piece", "value": "P"}], [9, null]], [[54, null], [55, {"type": "Piece", "value": "p"}], [46, {"type": "Piece", "value": "r"}], [47, null], [38, {"type": "Piece", "value": "p"}], [39, null]], [[9, null], [10, null], [11, null], [1, {"type": "Piece", "value": "R"}], [2, null], [3, {"type": "Piece", "value": "Q"}]], [[56, {"type": "Piece", "value": "r"}], [57, null], [48, null], [49, {"type": "Piece", "value": "p"}], [40, null], [41, {"type": "Piece", "value": "p"}]], [[54, null], [55, {"type": "Piece", "value": "p"}], [46, null], [47, null], [38, {"type": "Piece", "value": "p"}], [39, null]], [[16, {"type": "Piece", "value": "B"}], [17, {"type": "Piece", "value": "P"}], [8, {"type": "Piece", "value": "P"}], [9, null], [0, null], [1, {"type": "Piece", "value": "R"}]], [[61, {"type": "Piece", "value": "b"}], [62, {"type": "Piece", "value": "r"}], [63, null], [53, {"type": "Piece", "value": "p"}], [54, null], [55, {"type": "Piece", "value": "p"}], [45, {"type": "Piece", "value": "n"}], [46, null], [47, null]], [[53, {"type": "Piece", "value": "p"}], [54, null], [55, {"type": "Piece", "value": "p"}], [45, {"type": "Piece", "value": "n"}], [46, null], [47, null], [37, null], [38, {"type": "Piece", "value": "p"}], [39, null]], [[49, {"type": "Piece", "value": "p"}], [50, null], [51, {"type": "Piece", "value": "p"}], [41, {"type": "Piece", "value": "p"}], [42, null], [43, null], [33, null], [34, null], [35, null]], [[33, null], [34, null], [35, null], [25, {"type": "Piece", "value": "P"}], [26, null], [27, null], [17, {"type": "Piece", "value": "P"}], [18, null], [19, {"type": "Piece", "value": "P"}]], [[20, null], [21, null], [22, {"type": "Piece", "value": "P"}], [12, {"type": "Piece", "value": "P"}], [13, null], [14, {"type": "Piece", "value": "K"}], [4, {"type": "Piece", "value": "Q"}], [5, {"type": "Piece", "value": "B"}], [6, null]], [[33, null], [34, null], [35, null], [25, {"type": "Piece", "value": "P"}], [26, null], [27, null], [17, {"type": "Piece", "value": "P"}], [18, null], [19, {"type": "Piece", "value": "P"}]], [[37, null], [38, {"type": "Piece", "value": "N"}], [39, {"type": "Piece", "value": "n"}], [29, {"type": "Piece", "value": "P"}], [30, {"type": "Piece", "value": "P"}], [31, null], [21, null], [22, null], [23, {"type": "Piece", "value": "P"}]], [[54, {"type": "Piece", "value": "r"}], [55, null], [46, null], [47, {"type": "Piece", "value": "p"}], [38, {"type": "Piece", "value": "N"}], [39, {"type": "Piece", "value": "n"}]], [[13, null], [14, {"type": "Piece", "value": "K"}], [15, null], [5, {"type": "Piece", "value": "B"}], [6, null], [7, {"type": "Piece", "value": "R"}]], [[42, null], [43, null], [44, null], [34, null], [35, null], [36, null], [26, null], [27, null], [28, {"type": "Piece", "value": "P"}]], [[35, null], [36, null], [37, null], [27, null], [28, {"type": "Piece", "value": "P"}], [29, {"type": "Piece", "value": "P"}], [19, {"type": "Piece", "value": "P"}], [20, null], [21, null]], [[16, {"type": "Piece", "value": "B"}], [17, {"type": "Piece", "value": "P"}], [8, {"type": "Piece", "value": "P"}], [9, {"type": "Piece", "value": "R"}], [0, null], [1, null]], [[37, null], [38, null], [39, {"type": "Piece", "value": "r"}], [29, {"type": "Piece", "value": "P"}], [30, {"type": "Piece", "value": "P"}], [31, null], [21, null], [22, null], [23, {"type": "Piece", "value": "P"}]], [[54, null], [55, null], [46, null], [47, {"type": "Piece", "value": "p"}], [38, null], [39, {"type": "Piece", "value": "r"}]], [[40, {"type": "Piece", "value": "r"}], [41, {"type": "Piece", "value": "p"}], [32, null], [33, {"type": "Piece", "value": "P"}], [24, null], [25, null]], [[49, {"type": "Piece", "value": "p"}], [50, null], [51, {"type": "Piece", "value": "p"}], [41, {"type": "Piece", "value": "p"}], [42, null], [43, null], [33, {"type": "Piece", "value": "P"}], [34, null], [35, null]], [[56, null], [57, null], [48, null], [49, {"type": "Piece", "value": "p"}]], [[8, {"type": "Piece", "value": "p"}], [9, null], [0, null], [1, null]], [[56, null], [57, null], [58, {"type": "Piece", "value": "b"}], [48, null], [49, {"type": "Piece", "value": "p"}], [50, {"type": "Piece", "value": "q"}], [40, {"type": "Piece", "value": "r"}], [41, {"type": "Piece", "value": "p"}], [42, null]], [[32, null], [33, null], [24, null], [25, null], [16, {"type": "Piece", "value": "B"}], [17, null]], [[40, {"type": "Piece", "value": "r"}], [41, {"type": "Piece", "value": "Q"}], [32, null], [33, null], [24, null], [25, null]], [[58, {"type": "Piece", "value": "b"}], [59, null], [60, {"type": "Piece", "value": "k"}], [50, {"type": "Piece", "value": "q"}], [51, {"type": "Piece", "value": "p"}], [52, {"type": "Piece", "value": "p"}], [42, null], [43, null], [44, null]], [[44, null], [45, null], [46, null], [36, null], [37, null], [38, null], [28, {"type": "Piece", "value": "P"}], [29, {"type": "Piece", "value": "P"}], [30, {"type": "Piece", "value": "n"}]], [[49, {"type": "Piece", "value": "p"}], [50, null], [51, {"type": "Piece", "value": "p"}], [41, {"type": "Piece", "value": "Q"}], [42, null], [43, null], [33, null], [34, {"type": "Piece", "value": "q"}], [35, null]], [[62, null], [63, null], [54, null], [55, null]], [[24, null], [25, {"type": "Piece", "value": "Q"}], [26, null], [16, {"type": "Piece", "value": "B"}], [17, null], [18, null], [8, {"type": "Piece", "value": "p"}], [9, null], [10, null]], [[57, null], [58, {"type": "Piece", "value": "b"}], [59, null], [49, {"type": "Piece", "value": "p"}], [50, null], [51, {"type": "Piece", "value": "p"}]], [[54, null], [55, null], [46, null], [47, {"type": "Piece", "value": "p"}], [38, null], [39, null]], [[41, null], [42, null], [43, null], [33, {"type": "Piece", "value": "Q"}], [34, null], [35, null], [25, null], [26, null], [27, {"type": "Piece", "value": "P"}]], [[45, null], [46, null], [47, {"type": "Piece", "value": "p"}], [37, null], [38, null], [39, null], [29, {"type": "Piece", "value": "P"}], [30, {"type": "Piece", "value": "n"}], [31, null]]]}, "requested_moves": {"true": [{"type": "Move", "value": "g2g3"}, {"type": "Move", "value": "b2b4"}, {"type": "Move", "value": "h2h3"}, {"type": "Move", "value": "b1a3"}, {"type": "Move", "value": "b4c5"}, {"type": "Move", "value": "d2c3"}, {"type": "Move", "value": "f2f4"}, {"type": "Move", "value": "d2d3"}, {"type": "Move", "value": "a3c4"}, {"type": "Move", "value": "c4b6"}, {"type": "Move", "value": "c1a3"}, {"type": "Move", "value": "e1f2"}, {"type": "Move", "value": "a2b3"}, {"type": "Move", "value": "a1b1"}, {"type": "Move", "value": "c2b3"}, {"type": "Move", "value": "h3g4"}, {"type": "Move", "value": "b4a5"}, null, {"type": "Move", "value": "g3h4"}, {"type": "Move", "value": "b3a4"}, {"type": "Move", "value": "f2g2"}, {"type": "Move", "value": "f4e5"}, {"type": "Move", "value": "g3h4"}, {"type": "Move", "value": "d1e1"}, {"type": "Move", "value": "d3c4"}, {"type": "Move", "value": "g1f3"}, {"type": "Move", "value": "f3g5"}, {"type": "Move", "value": "g3g4"}, {"type": "Move", "value": "b4b5"}, {"type": "Move", "value": "e2e4"}, {"type": "Move", "value": "e1e2"}, {"type": "Move", "value": "b1b2"}, {"type": "Move", "value": "h1g1"}, {"type": "Move", "value": "e2e3"}, {"type": "Move", "value": "b2f2"}, {"type": "Move", "value": "e3d2"}, null, {"type": "Move", "value": "d2b4"}, {"type": "Move", "value": "g2g3"}, {"type": "Move", "value": "d3d4"}, {"type": "Move", "value": "b4b6"}, {"type": "Move", "value": "b5b6"}, {"type": "Move", "value": "d4c5"}, {"type": "Move", "value": "f1d3"}, {"type": "Move", "value": "e4d5"}, {"type": "Move", "value": "g3h2"}, {"type": "Move", "value": "b6b4"}, {"type": "Move", "value": "g1f1"}, {"type": "Move", "value": "f1b1"}, {"type": "Move", "value": "d3f1"}, {"type": "Move", "value": "b4b6"}, {"type": "Move", "value": "b5e5"}], "false": [{"type": "Move", "value": "b8a6"}, {"type": "Move", "value": "g7g5"}, {"type": "Move", "value": "d7e6"}, {"type": "Move", "value": "g8f6"}, {"type": "Move", "value": "a6c5"}, {"type": "Move", "value": "h8g8"}, {"type": "Move", "value": "f7g6"}, {"type": "Move", "value": "b7a6"}, {"type": "Move", "value": "c7b6"}, {"type": "Move", "value": "a7a6"}, {"type": "Move", "value": "b7b5"}, {"type": "Move", "value": "a6b5"}, {"type": "Move", "value": "c5b3"}, {"type": "Move", "value": "e7d6"}, {"type": "Move", "value": "g8g6"}, {"type": "Move", "value": "c7b6"}, {"type": "Move", "value": "a6a5"}, null, {"type": "Move", "value": "g6g8"}, {"type": "Move", "value": "d7e6"}, {"type": "Move", "value": "f7e6"}, {"type": "Move", "value": "a8a6"}, {"type": "Move", "value": "f7e6"}, {"type": "Move", "value": "g8g7"}, {"type": "Move", "value": "h7g6"}, {"type": "Move", "value": "f6h5"}, {"type": "Move", "value": "h7h6"}, {"type": "Move", "value": "a5a4"}, {"type": "Move", "value": "a6a8"}, {"type": "Move", "value": "g7g3"}, null, {"type": "Move", "value": "h5f6"}, {"type": "Move", "value": "a8a6"}, {"type": "Move", "value": "g5h5"}, {"type": "Move", "value": "a4b3"}, {"type": "Move", "value": "b3a2"}, {"type": "Move", "value": "a2b1b"}, {"type": "Move", "value": "f6g4"}, {"type": "Move", "value": "h5b5"}, {"type": "Move", "value": "d8c7"}, {"type": "Move", "value": "c7d8"}, {"type": "Move", "value": "d8c7"}, {"type": "Move", "value": "h6g5"}, {"type": "Move", "value": "a2b1"}, {"type": "Move", "value": "c7c5"}, {"type": "Move", "value": "a2b1r"}, {"type": "Move", "value": "a6e6"}, {"type": "Move", "value": "c5c6"}, {"type": "Move", "value": "e6e1"}, {"type": "Move", "value": "c6b5"}, {"type": "Move", "value": "e4c4"}, {"type": "Move", "value": "g4f2"}]}, "taken_moves": {"true": [{"type": "Move", "value": "g2g3"}, {"type": "Move", "value": "b2b4"}, {"type": "Move", "value": "h2h3"}, {"type": "Move", "value": "b1a3"}, null, null, {"type": "Move", "value": "f2f4"}, {"type": "Move", "value": "d2d3"}, {"type": "Move", "value": "a3c4"}, {"type": "Move", "value": "c4b6"}, {"type": "Move", "value": "c1a3"}, {"type": "Move", "value": "e1f2"}, null, {"type": "Move", "value": "a1b1"}, {"type": "Move", "value": "c2b3"}, null, null, null, null, null, {"type": "Move", "value": "f2g2"}, null, null, {"type": "Move", "value": "d1e1"}, null, {"type": "Move", "value": "g1f3"}, {"type": "Move", "value": "f3g5"}, {"type": "Move", "value": "g3g4"}, {"type": "Move", "value": "b4b5"}, {"type": "Move", "value": "e2e4"}, {"type": "Move", "value": "e1e2"}, {"type": "Move", "value": "b1b2"}, {"type": "Move", "value": "h1g1"}, {"type": "Move", "value": "e2e3"}, {"type": "Move", "value": "b2f2"}, {"type": "Move", "value": "e3d2"}, null, {"type": "Move", "value": "d2b4"}, {"type": "Move", "value": "g2g3"}, {"type": "Move", "value": "d3d4"}, {"type": "Move", "value": "b4b5"}, {"type": "Move", "value": "b5b6"}, null, {"type": "Move", "value": "f1d3"}, null, {"type": "Move", "value": "g3h2"}, {"type": "Move", "value": "b6b4"}, {"type": "Move", "value": "g1f1"}, {"type": "Move", "value": "f1b1"}, {"type": "Move", "value": "d3f1"}, {"type": "Move", "value": "b4b5"}, {"type": "Move", "value": "b5e5"}], "false": [{"type": "Move", "value": "b8a6"}, {"type": "Move", "value": "g7g5"}, null, {"type": "Move", "value": "g8f6"}, {"type": "Move", "value": "a6c5"}, {"type": "Move", "value": "h8g8"}, null, null, null, {"type": "Move", "value": "a7a6"}, null, null, {"type": "Move", "value": "c5b3"}, null, {"type": "Move", "value": "g8g6"}, {"type": "Move", "value": "c7b6"}, {"type": "Move", "value": "a6a5"}, null, {"type": "Move", "value": "g6g8"}, null, null, {"type": "Move", "value": "a8a6"}, null, {"type": "Move", "value": "g8g7"}, null, {"type": "Move", "value": "f6h5"}, {"type": "Move", "value": "h7h6"}, {"type": "Move", "value": "a5a4"}, {"type": "Move", "value": "a6a8"}, {"type": "Move", "value": "g7g5"}, null, {"type": "Move", "value": "h5f6"}, {"type": "Move", "value": "a8a6"}, {"type": "Move", "value": "g5h5"}, {"type": "Move", "value": "a4b3"}, {"type": "Move", "value": "b3a2"}, null, {"type": "Move", "value": "f6g4"}, {"type": "Move", "value": "h5b5"}, {"type": "Move", "value": "d8c7"}, {"type": "Move", "value": "c7d8"}, {"type": "Move", "value": "d8c7"}, null, null, {"type": "Move", "value": "c7c5"}, null, {"type": "Move", "value": "a6e6"}, {"type": "Move", "value": "c5c6"}, {"type": "Move", "value": "e6e4"}, {"type": "Move", "value": "c6b5"}, {"type": "Move", "value": "e4d4"}, {"type": "Move", "value": "g4f2"}]}, "capture_squares": {"true": [null, null, null, null, null, null, null, null, null, null, null, null, null, null, 17, null, null, null, null, null, null, null, null, null, null, null, 38, null, null, null, null, null, null, null, null, null, null, null, null, null, 33, 41, null, null, null, null, null, null, null, null, 33, null], "false": [null, null, null, null, null, null, null, null, null, null, null, null, null, null, null, 41, null, null, null, null, null, null, null, null, null, null, null, null, null, 38, null, null, null, null, 17, 8, null, 30, 33, null, null, null, null, null, null, null, null, null, 28, null, 27, 13]}, "fens_before_move": {"true": ["rnbqkbnr/pppppppp/8/8/8/8/PPPPPPPP/RNBQKBNR w KQkq - 0 1", "r1bqkbnr/pppppppp/n7/8/8/6P1/PPPPPP1P/RNBQKBNR w KQkq - 1 2", "r1bqkbnr/pppppp1p/n7/6p1/1P6/6P1/P1PPPP1P/RNBQKBNR w KQkq g6 0 3", "r1bqkbnr/pppppp1p/n7/6p1/1P6/6PP/P1PPPP2/RNBQKBNR w KQkq - 1 4", "r1bqkb1r/pppppp1p/n4n2/6p1/1P6/N5PP/P1PPPP2/R1BQKBNR w KQkq - 3 5", "r1bqkb1r/pppppp1p/5n2/2n3p1/1P6/N5PP/P1PPPP2/R1BQKBNR w KQkq - 5 6", "r1bqkbr1/pppppp1p/5n2/2n3p1/1P6/N5PP/P1PPPP2/R1BQKBNR w KQq - 7 7", "r1bqkbr1/pppppp1p/5n2/2n3p1/1P3P2/N5PP/P1PPP3/R1BQKBNR w KQq - 1 8", "r1bqkbr1/pppppp1p/5n2/2n3p1/1P3P2/N2P2PP/P1P1P3/R1BQKBNR w KQq - 1 9", "r1bqkbr1/pppppp1p/5n2/2n3p1/1PN2P2/3P2PP/P1P1P3/R1BQKBNR w KQq - 3 10", "r1bqkbr1/1ppppp1p/pN3n2/2n3p1/1P3P2/3P2PP/P1P1P3/R1BQKBNR w KQq - 0 11", "r1bqkbr1/1ppppp1p/pN3n2/2n3p1/1P3P2/B2P2PP/P1P1P3/R2QKBNR w KQq - 2 12", "r1bqkbr1/1ppppp1p/pN3n2/2n3p1/1P3P2/B2P2PP/P1P1PK2/R2Q1BNR w q - 4 13", "r1bqkbr1/1ppppp1p/pN3n2/6p1/1P3P2/Bn1P2PP/P1P1PK2/R2Q1BNR w q - 6 14", "r1bqkbr1/1ppppp1p/pN3n2/6p1/1P3P2/Bn1P2PP/P1P1PK2/1R1Q1BNR w q - 8 15", "r1bqkb2/1ppppp1p/pN3nr1/6p1/1P3P2/BP1P2PP/P3PK2/1R1Q1BNR w q - 1 16", "r1bqkb2/1p1ppp1p/pp3nr1/6p1/1P3P2/BP1P2PP/P3PK2/1R1Q1BNR w q - 0 17", "r1bqkb2/1p1ppp1p/1p3nr1/p5p1/1P3P2/BP1P2PP/P3PK2/1R1Q1BNR w q - 0 18", "r1bqkb2/1p1ppp1p/1p3nr1/p5p1/1P3P2/BP1P2PP/P3PK2/1R1Q1BNR w q - 2 19", "r1bqkbr1/1p1ppp1p/1p3n2/p5p1/1P3P2/BP1P2PP/P3PK2/1R1Q1BNR w q - 4 20", "r1bqkbr1/1p1ppp1p/1p3n2/p5p1/1P3P2/BP1P2PP/P3PK2/1R1Q1BNR w q - 6 21", "r1bqkbr1/1p1ppp1p/1p3n2/p5p1/1P3P2/BP1P2PP/P3P1K1/1R1Q1BNR w q - 8 22", "2bqkbr1/1p1ppp1p/rp3n2/p5p1/1P3P2/BP1P2PP/P3P1K1/1R1Q1BNR w - - 10 23", "2bqkbr1/1p1ppp1p/rp3n2/p5p1/1P3P2/BP1P2PP/P3P1K1/1R1Q1BNR w - - 12 24", "2bqkb2/1p1ppprp/rp3n2/p5p1/1P3P2/BP1P2PP/P3P1K1/1R2QBNR w - - 14 25", "2bqkb2/1p1ppprp/rp3n2/p5p1/1P3P2/BP1P2PP/P3P1K1/1R2QBNR w - - 16 26", "2bqkb2/1p1ppprp/rp6/p5pn/1P3P2/BP1P1NPP/P3P1K1/1R2QB1R w - - 18 27", "2bqkb2/1p1pppr1/rp5p/p5Nn/1P3P2/BP1P2PP/P3P1K1/1R2QB1R w - - 0 28", "2bqkb2/1p1pppr1/rp5p/6Nn/pP3PP1/BP1P3P/P3P1K1/1R2QB1R w - - 0 29", "r1bqkb2/1p1pppr1/1p5p/1P4Nn/p4PP1/BP1P3P/P3P1K1/1R2QB1R w - - 1 30", "r1bqkb2/1p1ppp2/1p5p/1P4rn/p3PPP1/BP1P3P/P5K1/1R2QB1R w - - 0 31", "r1bqkb2/1p1ppp2/1p5p/1P4rn/p3PPP1/BP1P3P/P3Q1K1/1R3B1R w - - 2 32", "r1bqkb2/1p1ppp2/1p3n1p/1P4r1/p3PPP1/BP1P3P/PR2Q1K1/5B1R w - - 4 33", "2bqkb2/1p1ppp2/rp3n1p/1P4r1/p3PPP1/BP1P3P/PR2Q1K1/5BR1 w - - 6 34", "2bqkb2/1p1ppp2/rp3n1p/1P5r/p3PPP1/BP1PQ2P/PR4K1/5BR1 w - - 8 35", "2bqkb2/1p1ppp2/rp3n1p/1P5r/4PPP1/Bp1PQ2P/P4RK1/5BR1 w - - 0 36", "2bqkb2/1p1ppp2/rp3n1p/1P5r/4PPP1/B2P3P/p2Q1RK1/5BR1 w - - 0 37", "2bqkb2/1p1ppp2/rp3n1p/1P5r/4PPP1/B2P3P/p2Q1RK1/5BR1 w - - 2 38", "2bqkb2/1p1ppp2/rp5p/1P5r/1Q2PPn1/B2P3P/p4RK1/5BR1 w - - 0 39", "2bqkb2/1p1ppp2/rp5p/1r6/1Q2PPn1/B2P2KP/p4R2/5BR1 w - - 0 40", "2b1kb2/1pqppp2/rp5p/1r6/1Q1PPPn1/B5KP/p4R2/5BR1 w - - 1 41", "2bqkb2/1p1ppp2/rp5p/1Q6/3PPPn1/B5KP/p4R2/5BR1 w - - 1 42", "2b1kb2/1pqppp2/rQ5p/8/3PPPn1/B5KP/p4R2/5BR1 w - - 1 43", "2b1kb2/1pqppp2/rQ5p/8/3PPPn1/B5KP/p4R2/5BR1 w - - 3 44", "2b1kb2/1pqppp2/rQ5p/8/3PPPn1/B2B2KP/p4R2/6R1 w - - 5 45", "2b1kb2/1p1ppp2/rQ5p/2q5/3PPPn1/B2B2KP/p4R2/6R1 w - - 7 46", "2b1kb2/1p1ppp2/rQ5p/2q5/3PPPn1/B2B3P/p4R1K/6R1 w - - 9 47", "2b1kb2/1p1ppp2/4r2p/2q5/1Q1PPPn1/B2B3P/p4R1K/6R1 w - - 11 48", "2b1kb2/1p1ppp2/2q1r2p/8/1Q1PPPn1/B2B3P/p4R1K/5R2 w - - 13 49", "2b1kb2/1p1ppp2/2q4p/8/1Q1PrPn1/B2B3P/p4R1K/1R6 w - - 0 50", "2b1kb2/1p1ppp2/7p/1q6/1Q1PrPn1/B6P/p4R1K/1R3B2 w - - 2 51", "2b1kb2/1p1ppp2/7p/1Q6/3r1Pn1/B6P/p4R1K/1R3B2 w - - 0 52"], "false": ["rnbqkbnr/pppppppp/8/8/8/6P1/PPPPPP1P/RNBQKBNR b KQkq - 0 1", "r1bqkbnr/pppppppp/n7/8/1P6/6P1/P1PPPP1P/RNBQKBNR b KQkq b3 0 2", "r1bqkbnr/pppppp1p/n7/6p1/1P6/6PP/P1PPPP2/RNBQKBNR b KQkq - 0 3", "r1bqkbnr/pppppp1p/n7/6p1/1P6/N5PP/P1PPPP2/R1BQKBNR b KQkq - 2 4", "r1bqkb1r/pppppp1p/n4n2/6p1/1P6/N5PP/P1PPPP2/R1BQKBNR b KQkq - 4 5", "r1bqkb1r/pppppp1p/5n2/2n3p1/1P6/N5PP/P1PPPP2/R1BQKBNR b KQkq - 6 6", "r1bqkbr1/pppppp1p/5n2/2n3p1/1P3P2/N5PP/P1PPP3/R1BQKBNR b KQq f3 0 7", "r1bqkbr1/pppppp1p/5n2/2n3p1/1P3P2/N2P2PP/P1P1P3/R1BQKBNR b KQq - 0 8", "r1bqkbr1/pppppp1p/5n2/2n3p1/1PN2P2/3P2PP/P1P1P3/R1BQKBNR b KQq - 2 9", "r1bqkbr1/pppppp1p/1N3n2/2n3p1/1P3P2/3P2PP/P1P1P3/R1BQKBNR b KQq - 4 10", "r1bqkbr1/1ppppp1p/pN3n2/2n3p1/1P3P2/B2P2PP/P1P1P3/R2QKBNR b KQq - 1 11", "r1bqkbr1/1ppppp1p/pN3n2/2n3p1/1P3P2/B2P2PP/P1P1PK2/R2Q1BNR b q - 3 12", "r1bqkbr1/1ppppp1p/pN3n2/2n3p1/1P3P2/B2P2PP/P1P1PK2/R2Q1BNR b q - 5 13", "r1bqkbr1/1ppppp1p/pN3n2/6p1/1P3P2/Bn1P2PP/P1P1PK2/1R1Q1BNR b q - 7 14", "r1bqkbr1/1ppppp1p/pN3n2/6p1/1P3P2/BP1P2PP/P3PK2/1R1Q1BNR b q - 0 15", "r1bqkb2/1ppppp1p/pN3nr1/6p1/1P3P2/BP1P2PP/P3PK2/1R1Q1BNR b q - 2 16", "r1bqkb2/1p1ppp1p/pp3nr1/6p1/1P3P2/BP1P2PP/P3PK2/1R1Q1BNR b q - 1 17", "r1bqkb2/1p1ppp1p/1p3nr1/p5p1/1P3P2/BP1P2PP/P3PK2/1R1Q1BNR b q - 1 18", "r1bqkb2/1p1ppp1p/1p3nr1/p5p1/1P3P2/BP1P2PP/P3PK2/1R1Q1BNR b q - 3 19", "r1bqkbr1/1p1ppp1p/1p3n2/p5p1/1P3P2/BP1P2PP/P3PK2/1R1Q1BNR b q - 5 20", "r1bqkbr1/1p1ppp1p/1p3n2/p5p1/1P3P2/BP1P2PP/P3P1K1/1R1Q1BNR b q - 7 21", "r1bqkbr1/1p1ppp1p/1p3n2/p5p1/1P3P2/BP1P2PP/P3P1K1/1R1Q1BNR b q - 9 22", "2bqkbr1/1p1ppp1p/rp3n2/p5p1/1P3P2/BP1P2PP/P3P1K1/1R1Q1BNR b - - 11 23", "2bqkbr1/1p1ppp1p/rp3n2/p5p1/1P3P2/BP1P2PP/P3P1K1/1R2QBNR b - - 13 24", "2bqkb2/1p1ppprp/rp3n2/p5p1/1P3P2/BP1P2PP/P3P1K1/1R2QBNR b - - 15 25", "2bqkb2/1p1ppprp/rp3n2/p5p1/1P3P2/BP1P1NPP/P3P1K1/1R2QB1R b - - 17 26", "2bqkb2/1p1ppprp/rp6/p5Nn/1P3P2/BP1P2PP/P3P1K1/1R2QB1R b - - 0 27", "2bqkb2/1p1pppr1/rp5p/p5Nn/1P3PP1/BP1P3P/P3P1K1/1R2QB1R b - - 0 28", "2bqkb2/1p1pppr1/rp5p/1P4Nn/p4PP1/BP1P3P/P3P1K1/1R2QB1R b - - 0 29", "r1bqkb2/1p1pppr1/1p5p/1P4Nn/p3PPP1/BP1P3P/P5K1/1R2QB1R b - e3 0 30", "r1bqkb2/1p1ppp2/1p5p/1P4rn/p3PPP1/BP1P3P/P3Q1K1/1R3B1R b - - 1 31", "r1bqkb2/1p1ppp2/1p5p/1P4rn/p3PPP1/BP1P3P/PR2Q1K1/5B1R b - - 3 32", "r1bqkb2/1p1ppp2/1p3n1p/1P4r1/p3PPP1/BP1P3P/PR2Q1K1/5BR1 b - - 5 33", "2bqkb2/1p1ppp2/rp3n1p/1P4r1/p3PPP1/BP1PQ2P/PR4K1/5BR1 b - - 7 34", "2bqkb2/1p1ppp2/rp3n1p/1P5r/p3PPP1/BP1PQ2P/P4RK1/5BR1 b - - 9 35", "2bqkb2/1p1ppp2/rp3n1p/1P5r/4PPP1/Bp1P3P/P2Q1RK1/5BR1 b - - 1 36", "2bqkb2/1p1ppp2/rp3n1p/1P5r/4PPP1/B2P3P/p2Q1RK1/5BR1 b - - 1 37", "2bqkb2/1p1ppp2/rp3n1p/1P5r/1Q2PPP1/B2P3P/p4RK1/5BR1 b - - 3 38", "2bqkb2/1p1ppp2/rp5p/1P5r/1Q2PPn1/B2P2KP/p4R2/5BR1 b - - 1 39", "2bqkb2/1p1ppp2/rp5p/1r6/1Q1PPPn1/B5KP/p4R2/5BR1 b - - 0 40", "2b1kb2/1pqppp2/rp5p/1Q6/3PPPn1/B5KP/p4R2/5BR1 b - - 0 41", "2bqkb2/1p1ppp2/rQ5p/8/3PPPn1/B5KP/p4R2/5BR1 b - - 0 42", "2b1kb2/1pqppp2/rQ5p/8/3PPPn1/B5KP/p4R2/5BR1 b - - 2 43", "2b1kb2/1pqppp2/rQ5p/8/3PPPn1/B2B2KP/p4R2/6R1 b - - 4 44", "2b1kb2/1pqppp2/rQ5p/8/3PPPn1/B2B2KP/p4R2/6R1 b - - 6 45", "2b1kb2/1p1ppp2/rQ5p/2q5/3PPPn1/B2B3P/p4R1K/6R1 b - - 8 46", "2b1kb2/1p1ppp2/r6p/2q5/1Q1PPPn1/B2B3P/p4R1K/6R1 b - - 10 47", "2b1kb2/1p1ppp2/4r2p/2q5/1Q1PPPn1/B2B3P/p4R1K/5R2 b - - 12 48", "2b1kb2/1p1ppp2/2q1r2p/8/1Q1PPPn1/B2B3P/p4R1K/1R6 b - - 14 49", "2b1kb2/1p1ppp2/2q4p/8/1Q1PrPn1/B6P/p4R1K/1R3B2 b - - 1 50", "2b1kb2/1p1ppp2/7p/1Q6/3PrPn1/B6P/p4R1K/1R3B2 b - - 0 51", "2b1kb2/1p1ppp2/7p/4Q3/3r1Pn1/B6P/p4R1K/1R3B2 b - - 1 52"]}, "fens_after_move": {"true": ["rnbqkbnr/pppppppp/8/8/8/6P1/PPPPPP1P/RNBQKBNR b KQkq - 0 1", "r1bqkbnr/pppppppp/n7/8/1P6/6P1/P1PPPP1P/RNBQKBNR b KQkq b3 0 2", "r1bqkbnr/pppppp1p/n7/6p1/1P6/6PP/P1PPPP2/RNBQKBNR b KQkq - 0 3", "r1bqkbnr/pppppp1p/n7/6p1/1P6/N5PP/P1PPPP2/R1BQKBNR b KQkq - 2 4", "r1bqkb1r/pppppp1p/n4n2/6p1/1P6/N5PP/P1PPPP2/R1BQKBNR b KQkq - 4 5", "r1bqkb1r/pppppp1p/5n2/2n3p1/1P6/N5PP/P1PPPP2/R1BQKBNR b KQkq - 6 6", "r1bqkbr1/pppppp1p/5n2/2n3p1/1P3P2/N5PP/P1PPP3/R1BQKBNR b KQq f3 0 7", "r1bqkbr1/pppppp1p/5n2/2n3p1/1P3P2/N2P2PP/P1P1P3/R1BQKBNR b KQq - 0 8", "r1bqkbr1/pppppp1p/5n2/2n3p1/1PN2P2/3P2PP/P1P1P3/R1BQKBNR b KQq - 2 9", "r1bqkbr1/pppppp1p/1N3n2/2n3p1/1P3P2/3P2PP/P1P1P3/R1BQKBNR b KQq - 4 10", "r1bqkbr1/1ppppp1p/pN3n2/2n3p1/1P3P2/B2P2PP/P1P1P3/R2QKBNR b KQq - 1 11", "r1bqkbr1/1ppppp1p/pN3n2/2n3p1/1P3P2/B2P2PP/P1P1PK2/R2Q1BNR b q - 3 12", "r1bqkbr1/1ppppp1p/pN3n2/2n3p1/1P3P2/B2P2PP/P1P1PK2/R2Q1BNR b q - 5 13", "r1bqkbr1/1ppppp1p/pN3n2/6p1/1P3P2/Bn1P2PP/P1P1PK2/1R1Q1BNR b q - 7 14", "r1bqkbr1/1ppppp1p/pN3n2/6p1/1P3P2/BP1P2PP/P3PK2/1R1Q1BNR b q - 0 15", "r1bqkb2/1ppppp1p/pN3nr1/6p1/1P3P2/BP1P2PP/P3PK2/1R1Q1BNR b q - 2 16", "r1bqkb2/1p1ppp1p/pp3nr1/6p1/1P3P2/BP1P2PP/P3PK2/1R1Q1BNR b q - 1 17", "r1bqkb2/1p1ppp1p/1p3nr1/p5p1/1P3P2/BP1P2PP/P3PK2/1R1Q1BNR b q - 1 18", "r1bqkb2/1p1ppp1p/1p3nr1/p5p1/1P3P2/BP1P2PP/P3PK2/1R1Q1BNR b q - 3 19", "r1bqkbr1/1p1ppp1p/1p3n2/p5p1/1P3P2/BP1P2PP/P3PK2/1R1Q1BNR b q - 5 20", "r1bqkbr1/1p1ppp1p/1p3n2/p5p1/1P3P2/BP1P2PP/P3P1K1/1R1Q1BNR b q - 7 21", "r1bqkbr1/1p1ppp1p/1p3n2/p5p1/1P3P2/BP1P2PP/P3P1K1/1R1Q1BNR b q - 9 22", "2bqkbr1/1p1ppp1p/rp3n2/p5p1/1P3P2/BP1P2PP/P3P1K1/1R1Q1BNR b - - 11 23", "2bqkbr1/1p1ppp1p/rp3n2/p5p1/1P3P2/BP1P2PP/P3P1K1/1R2QBNR b - - 13 24", "2bqkb2/1p1ppprp/rp3n2/p5p1/1P3P2/BP1P2PP/P3P1K1/1R2QBNR b - - 15 25", "2bqkb2/1p1ppprp/rp3n2/p5p1/1P3P2/BP1P1NPP/P3P1K1/1R2QB1R b - - 17 26", "2bqkb2/1p1ppprp/rp6/p5Nn/1P3P2/BP1P2PP/P3P1K1/1R2QB1R b - - 0 27", "2bqkb2/1p1pppr1/rp5p/p5Nn/1P3PP1/BP1P3P/P3P1K1/1R2QB1R b - - 0 28", "2bqkb2/1p1pppr1/rp5p/1P4Nn/p4PP1/BP1P3P/P3P1K1/1R2QB1R b - - 0 29", "r1bqkb2/1p1pppr1/1p5p/1P4Nn/p3PPP1/BP1P3P/P5K1/1R2QB1R b - e3 0 30", "r1bqkb2/1p1ppp2/1p5p/1P4rn/p3PPP1/BP1P3P/P3Q1K1/1R3B1R b - - 1 31", "r1bqkb2/1p1ppp2/1p5p/1P4rn/p3PPP1/BP1P3P/PR2Q1K1/5B1R b - - 3 32", "r1bqkb2/1p1ppp2/1p3n1p/1P4r1/p3PPP1/BP1P3P/PR2Q1K1/5BR1 b - - 5 33", "2bqkb2/1p1ppp2/rp3n1p/1P4r1/p3PPP1/BP1PQ2P/PR4K1/5BR1 b - - 7 34", "2bqkb2/1p1ppp2/rp3n1p/1P5r/p3PPP1/BP1PQ2P/P4RK1/5BR1 b - - 9 35", "2bqkb2/1p1ppp2/rp3n1p/1P5r/4PPP1/Bp1P3P/P2Q1RK1/5BR1 b - - 1 36", "2bqkb2/1p1ppp2/rp3n1p/1P5r/4PPP1/B2P3P/p2Q1RK1/5BR1 b - - 1 37", "2bqkb2/1p1ppp2/rp3n1p/1P5r/1Q2PPP1/B2P3P/p4RK1/5BR1 b - - 3 38", "2bqkb2/1p1ppp2/rp5p/1P5r/1Q2PPn1/B2P2KP/p4R2/5BR1 b - - 1 39", "2bqkb2/1p1ppp2/rp5p/1r6/1Q1PPPn1/B5KP/p4R2/5BR1 b - - 0 40", "2b1kb2/1pqppp2/rp5p/1Q6/3PPPn1/B5KP/p4R2/5BR1 b - - 0 41", "2bqkb2/1p1ppp2/rQ5p/8/3PPPn1/B5KP/p4R2/5BR1 b - - 0 42", "2b1kb2/1pqppp2/rQ5p/8/3PPPn1/B5KP/p4R2/5BR1 b - - 2 43", "2b1kb2/1pqppp2/rQ5p/8/3PPPn1/B2B2KP/p4R2/6R1 b - - 4 44", "2b1kb2/1pqppp2/rQ5p/8/3PPPn1/B2B2KP/p4R2/6R1 b - - 6 45", "2b1kb2/1p1ppp2/rQ5p/2q5/3PPPn1/B2B3P/p4R1K/6R1 b - - 8 46", "2b1kb2/1p1ppp2/r6p/2q5/1Q1PPPn1/B2B3P/p4R1K/6R1 b - - 10 47", "2b1kb2/1p1ppp2/4r2p/2q5/1Q1PPPn1/B2B3P/p4R1K/5R2 b - - 12 48", "2b1kb2/1p1ppp2/2q1r2p/8/1Q1PPPn1/B2B3P/p4R1K/1R6 b - - 14 49", "2b1kb2/1p1ppp2/2q4p/8/1Q1PrPn1/B6P/p4R1K/1R3B2 b - - 1 50", "2b1kb2/1p1ppp2/7p/1Q6/3PrPn1/B6P/p4R1K/1R3B2 b - - 0 51", "2b1kb2/1p1ppp2/7p/4Q3/3r1Pn1/B6P/p4R1K/1R3B2 b - - 1 52"], "false": ["r1bqkbnr/pppppppp/n7/8/8/6P1/PPPPPP1P/RNBQKBNR w KQkq - 1 2", "r1bqkbnr/pppppp1p/n7/6p1/1P6/6P1/P1PPPP1P/RNBQKBNR w KQkq g6 0 3", "r1bqkbnr/pppppp1p/n7/6p1/1P6/6PP/P1PPPP2/RNBQKBNR w KQkq - 1 4", "r1bqkb1r/pppppp1p/n4n2/6p1/1P6/N5PP/P1PPPP2/R1BQKBNR w KQkq - 3 5", "r1bqkb1r/pppppp1p/5n2/2n3p1/1P6/N5PP/P1PPPP2/R1BQKBNR w KQkq - 5 6", "r1bqkbr1/pppppp1p/5n2/2n3p1/1P6/N5PP/P1PPPP2/R1BQKBNR w KQq - 7 7", "r1bqkbr1/pppppp1p/5n2/2n3p1/1P3P2/N5PP/P1PPP3/R1BQKBNR w KQq - 1 8", "r1bqkbr1/pppppp1p/5n2/2n3p1/1P3P2/N2P2PP/P1P1P3/R1BQKBNR w KQq - 1 9", "r1bqkbr1/pppppp1p/5n2/2n3p1/1PN2P2/3P2PP/P1P1P3/R1BQKBNR w KQq - 3 10", "r1bqkbr1/1ppppp1p/pN3n2/2n3p1/1P3P2/3P2PP/P1P1P3/R1BQKBNR w KQq - 0 11", "r1bqkbr1/1ppppp1p/pN3n2/2n3p1/1P3P2/B2P2PP/P1P1P3/R2QKBNR w KQq - 2 12", "r1bqkbr1/1ppppp1p/pN3n2/2n3p1/1P3P2/B2P2PP/P1P1PK2/R2Q1BNR w q - 4 13", "r1bqkbr1/1ppppp1p/pN3n2/6p1/1P3P2/Bn1P2PP/P1P1PK2/R2Q1BNR w q - 6 14", "r1bqkbr1/1ppppp1p/pN3n2/6p1/1P3P2/Bn1P2PP/P1P1PK2/1R1Q1BNR w q - 8 15", "r1bqkb2/1ppppp1p/pN3nr1/6p1/1P3P2/BP1P2PP/P3PK2/1R1Q1BNR w q - 1 16", "r1bqkb2/1p1ppp1p/pp3nr1/6p1/1P3P2/BP1P2PP/P3PK2/1R1Q1BNR w q - 0 17", "r1bqkb2/1p1ppp1p/1p3nr1/p5p1/1P3P2/BP1P2PP/P3PK2/1R1Q1BNR w q - 0 18", "r1bqkb2/1p1ppp1p/1p3nr1/p5p1/1P3P2/BP1P2PP/P3PK2/1R1Q1BNR w q - 2 19", "r1bqkbr1/1p1ppp1p/1p3n2/p5p1/1P3P2/BP1P2PP/P3PK2/1R1Q1BNR w q - 4 20", "r1bqkbr1/1p1ppp1p/1p3n2/p5p1/1P3P2/BP1P2PP/P3PK2/1R1Q1BNR w q - 6 21", "r1bqkbr1/1p1ppp1p/1p3n2/p5p1/1P3P2/BP1P2PP/P3P1K1/1R1Q1BNR w q - 8 22", "2bqkbr1/1p1ppp1p/rp3n2/p5p1/1P3P2/BP1P2PP/P3P1K1/1R1Q1BNR w - - 10 23", "2bqkbr1/1p1ppp1p/rp3n2/p5p1/1P3P2/BP1P2PP/P3P1K1/1R1Q1BNR w - - 12 24", "2bqkb2/1p1ppprp/rp3n2/p5p1/1P3P2/BP1P2PP/P3P1K1/1R2QBNR w - - 14 25", "2bqkb2/1p1ppprp/rp3n2/p5p1/1P3P2/BP1P2PP/P3P1K1/1R2QBNR w - - 16 26", "2bqkb2/1p1ppprp/rp6/p5pn/1P3P2/BP1P1NPP/P3P1K1/1R2QB1R w - - 18 27", "2bqkb2/1p1pppr1/rp5p/p5Nn/1P3P2/BP1P2PP/P3P1K1/1R2QB1R w - - 0 28", "2bqkb2/1p1pppr1/rp5p/6Nn/pP3PP1/BP1P3P/P3P1K1/1R2QB1R w - - 0 29", "r1bqkb2/1p1pppr1/1p5p/1P4Nn/p4PP1/BP1P3P/P3P1K1/1R2QB1R w - - 1 30", "r1bqkb2/1p1ppp2/1p5p/1P4rn/p3PPP1/BP1P3P/P5K1/1R2QB1R w - - 0 31", "r1bqkb2/1p1ppp2/1p5p/1P4rn/p3PPP1/BP1P3P/P3Q1K1/1R3B1R w - - 2 32", "r1bqkb2/1p1ppp2/1p3n1p/1P4r1/p3PPP1/BP1P3P/PR2Q1K1/5B1R w - - 4 33", "2bqkb2/1p1ppp2/rp3n1p/1P4r1/p3PPP1/BP1P3P/PR2Q1K1/5BR1 w - - 6 34", "2bqkb2/1p1ppp2/rp3n1p/1P5r/p3PPP1/BP1PQ2P/PR4K1/5BR1 w - - 8 35", "2bqkb2/1p1ppp2/rp3n1p/1P5r/4PPP1/Bp1PQ2P/P4RK1/5BR1 w - - 0 36", "2bqkb2/1p1ppp2/rp3n1p/1P5r/4PPP1/B2P3P/p2Q1RK1/5BR1 w - - 0 37", "2bqkb2/1p1ppp2/rp3n1p/1P5r/4PPP1/B2P3P/p2Q1RK1/5BR1 w - - 2 38", "2bqkb2/1p1ppp2/rp5p/1P5r/1Q2PPn1/B2P3P/p4RK1/5BR1 w - - 0 39", "2bqkb2/1p1ppp2/rp5p/1r6/1Q2PPn1/B2P2KP/p4R2/5BR1 w - - 0 40", "2b1kb2/1pqppp2/rp5p/1r6/1Q1PPPn1/B5KP/p4R2/5BR1 w - - 1 41", "2bqkb2/1p1ppp2/rp5p/1Q6/3PPPn1/B5KP/p4R2/5BR1 w - - 1 42", "2b1kb2/1pqppp2/rQ5p/8/3PPPn1/B5KP/p4R2/5BR1 w - - 1 43", "2b1kb2/1pqppp2/rQ5p/8/3PPPn1/B5KP/p4R2/5BR1 w - - 3 44", "2b1kb2/1pqppp2/rQ5p/8/3PPPn1/B2B2KP/p4R2/6R1 w - - 5 45", "2b1kb2/1p1ppp2/rQ5p/2q5/3PPPn1/B2B2KP/p4R2/6R1 w - - 7 46", "2b1kb2/1p1ppp2/rQ5p/2q5/3PPPn1/B2B3P/p4R1K/6R1 w - - 9 47", "2b1kb2/1p1ppp2/4r2p/2q5/1Q1PPPn1/B2B3P/p4R1K/6R1 w - - 11 48", "2b1kb2/1p1ppp2/2q1r2p/8/1Q1PPPn1/B2B3P/p4R1K/5R2 w - - 13 49", "2b1kb2/1p1ppp2/2q4p/8/1Q1PrPn1/B2B3P/p4R1K/1R6 w - - 0 50", "2b1kb2/1p1ppp2/7p/1q6/1Q1PrPn1/B6P/p4R1K/1R3B2 w - - 2 51", "2b1kb2/1p1ppp2/7p/1Q6/3r1Pn1/B6P/p4R1K/1R3B2 w - - 0 52", "2b1kb2/1p1ppp2/7p/4Q3/3r1P2/B6P/p4n1K/1R3B2 w - - 0 53"]}, "winner_color": false, "win_reason": {"type": "WinReason", "value": "TIMEOUT"}}